selethon/__init__.py
selethon/__version__.py
selethon/selethon.py
selethon-1.1.1.dist-info/METADATA
selethon-1.1.1.dist-info/RECORD
selethon-1.1.1.dist-info/WHEEL
selethon-1.1.1.dist-info/entry_points.txt
selethon-1.1.1.dist-info/top_level.txt
