Metadata-Version: 2.1
Name: selethon
Version: 1.1.1
Summary: automated controll website
Home-page: UNKNOWN
Author: Thanawat Petchuen
Author-email: thanawat1petchuen@gmail.com
License: MIT
Platform: UNKNOWN
Classifier: License :: OSI Approved :: MIT License
Classifier: Programming Language :: Python
Classifier: Programming Language :: Python :: 3
Classifier: Programming Language :: Python :: 3.6
Classifier: Programming Language :: Python :: Implementation :: CPython
Classifier: Programming Language :: Python :: Implementation :: PyPy
Requires-Python: >=3.6.0
Requires-Dist: selenium
Requires-Dist: webdrivermanager
